odoo/addons/web_timeline/README.rst
odoo/addons/web_timeline/__init__.py
odoo/addons/web_timeline/__manifest__.py
odoo/addons/web_timeline/i18n/ca.po
odoo/addons/web_timeline/i18n/de.po
odoo/addons/web_timeline/i18n/es.po
odoo/addons/web_timeline/i18n/fr.po
odoo/addons/web_timeline/i18n/hr.po
odoo/addons/web_timeline/i18n/nl_NL.po
odoo/addons/web_timeline/i18n/pt.po
odoo/addons/web_timeline/i18n/pt_BR.po
odoo/addons/web_timeline/i18n/web_timeline.pot
odoo/addons/web_timeline/i18n/zh_CN.po
odoo/addons/web_timeline/models/__init__.py
odoo/addons/web_timeline/models/ir_view.py
odoo/addons/web_timeline/readme/CONFIGURE.rst
odoo/addons/web_timeline/readme/CONTRIBUTORS.rst
odoo/addons/web_timeline/readme/CREDITS.rst
odoo/addons/web_timeline/readme/DESCRIPTION.rst
odoo/addons/web_timeline/readme/ROADMAP.rst
odoo/addons/web_timeline/readme/USAGE.rst
odoo/addons/web_timeline/static/description/icon.png
odoo/addons/web_timeline/static/description/index.html
odoo/addons/web_timeline/static/lib/vis/vis-timeline-graph2d.min.css
odoo/addons/web_timeline/static/lib/vis/vis-timeline-graph2d.min.js
odoo/addons/web_timeline/static/src/css/web_timeline.css
odoo/addons/web_timeline/static/src/js/timeline_canvas.js
odoo/addons/web_timeline/static/src/js/timeline_controller.js
odoo/addons/web_timeline/static/src/js/timeline_model.js
odoo/addons/web_timeline/static/src/js/timeline_renderer.js
odoo/addons/web_timeline/static/src/js/timeline_view.js
odoo/addons/web_timeline/static/src/xml/web_timeline.xml
odoo/addons/web_timeline/views/web_timeline.xml
odoo12_addon_web_timeline-12.0.1.1.2.dist-info/METADATA
odoo12_addon_web_timeline-12.0.1.1.2.dist-info/WHEEL
odoo12_addon_web_timeline-12.0.1.1.2.dist-info/top_level.txt
odoo12_addon_web_timeline-12.0.1.1.2.dist-info/RECORD
